dbcode/__init__.py
dbcode/config.py
dbcode/database.py
dbcode/utils.py
database_code-0.0.1.dist-info/LICENSE
database_code-0.0.1.dist-info/METADATA
database_code-0.0.1.dist-info/WHEEL
database_code-0.0.1.dist-info/top_level.txt
database_code-0.0.1.dist-info/RECORD
