Metadata-Version: 2.1
Name: database-code
Version: 0.0.1
Summary: database-code
Home-page: UNKNOWN
Author: V. Kalinin
Author-email: <vkalininz@mail.ru>
License: UNKNOWN
Keywords: python,database,sqlite3,postgresql
Platform: UNKNOWN
Classifier: Development Status :: 1 - Planning
Classifier: Intended Audience :: Developers
Classifier: Programming Language :: Python :: 3
Classifier: Operating System :: Unix
Classifier: Operating System :: MacOS :: MacOS X
Classifier: Operating System :: Microsoft :: Windows
License-File: LICENSE
Requires-Dist: psycopg2
Requires-Dist: psycopg2-binary
